agentsphere_mcp/__init__.py
agentsphere_mcp/asphere_mcp_stdio.py
agentsphere_mcp/logger.py
agentsphere_mcp/sandbox_pty_manager.py
agentsphere_mcp/single_sandbox_manager.py
agentsphere_mcp/tlv_protocol.py
agentsphere_mcp_server-1.9.1.dist-info/METADATA
agentsphere_mcp_server-1.9.1.dist-info/WHEEL
agentsphere_mcp_server-1.9.1.dist-info/entry_points.txt
agentsphere_mcp_server-1.9.1.dist-info/licenses/LICENSE
agentsphere_mcp_server-1.9.1.dist-info/RECORD
