Metadata-Version: 2.4
Name: agentsphere-mcp-server
Version: 1.9.1
Summary: mcp server for agentsphere sandbox
Project-URL: Homepage, https://www.agentsphere.run/home
Author-email: Yutong Xu <ytxucn@isoftstone.com>
License: MIT License
License-File: LICENSE
Keywords: agentsphere,mcp,sandbox
Classifier: Development Status :: 4 - Beta
Classifier: Intended Audience :: End Users/Desktop
Classifier: Programming Language :: Python :: 3
Requires-Python: >=3.12
Requires-Dist: agentsphere==0.1.6
Requires-Dist: fastmcp==2.12.4
Requires-Dist: platformdirs==4.3.8
